{"GlobalPropertiesHash":"kebubVDmfMIvPXfy/+HL/hroQW/dSwAaSETqzIyVYD4=","FingerprintPatternsHash":"gq3WsqcKBUGTSNle7RKKyXRIwh7M8ccEqOqYvIzoM04=","PropertyOverridesHash":"8ZRc1sGeVrPBx4lD717BgRaQekyh78QKV9SKsdt638U=","InputHashes":["1ukv1PTMZz1PKYr7POSKd6Zpqhm2vSfLUeQokASHYfM=","No5aFJ9XtOPI0YWFvaQy8mjfEISNjIceYLAgTELLT94=","7KfuCFROkTKIgfEhtugstl6C8kijLsLd2eWSRX2zu1s=","Z50HhjeWF\u002Bx6wimBF3/tpvDn76NKf\u002BeZgIivd7kxu5A="],"CachedAssets":{"1ukv1PTMZz1PKYr7POSKd6Zpqhm2vSfLUeQokASHYfM=":{"Identity":"C:\\Users\\EnaNguyen\\source\\repos\\ToDo\\ToDo\\wwwroot\\template\\validation\\validation.css","SourceId":"ToDo","SourceType":"Discovered","ContentRoot":"C:\\Users\\EnaNguyen\\source\\repos\\ToDo\\ToDo\\wwwroot\\","BasePath":"/","RelativePath":"template/validation/validation#[.{fingerprint}]?.css","AssetKind":"All","AssetMode":"All","AssetRole":"Primary","AssetMergeBehavior":null,"AssetMergeSource":"","RelatedAsset":null,"AssetTraitName":null,"AssetTraitValue":null,"Fingerprint":"8kv5j9dfob","Integrity":"CHbofWYarDUb7hmVNMI1vWPzgE1rilvMHs5nxdWkGGg=","CopyToOutputDirectory":"Never","CopyToPublishDirectory":"PreserveNewest","OriginalItemSpec":"wwwroot\\template\\validation\\validation.css","FileLength":689,"LastWriteTime":"2026-01-09T03:36:20.5540574+00:00"},"No5aFJ9XtOPI0YWFvaQy8mjfEISNjIceYLAgTELLT94=":{"Identity":"C:\\Users\\EnaNguyen\\source\\repos\\ToDo\\ToDo\\wwwroot\\template\\validation\\validation.html","SourceId":"ToDo","SourceType":"Discovered","ContentRoot":"C:\\Users\\EnaNguyen\\source\\repos\\ToDo\\ToDo\\wwwroot\\","BasePath":"/","RelativePath":"template/validation/validation#[.{fingerprint}]?.html","AssetKind":"All","AssetMode":"All","AssetRole":"Primary","AssetMergeBehavior":null,"AssetMergeSource":"","RelatedAsset":null,"AssetTraitName":null,"AssetTraitValue":null,"Fingerprint":"9v9wt6scaq","Integrity":"9c5gXHTxmDohzO4CncLiDEIX4/WWz7Kma694EKznTTo=","CopyToOutputDirectory":"Never","CopyToPublishDirectory":"PreserveNewest","OriginalItemSpec":"wwwroot\\template\\validation\\validation.html","FileLength":722,"LastWriteTime":"2026-01-09T04:26:43.2694427+00:00"}},"CachedCopyCandidates":{}}